{"terminationconditions":[],"fragments":[{"bound":{"hasBound":false,"limit":100},"preconditions":["Parcel[new]"],"_id":"5cfc10241991f20025b29ab9","name":"Create Offer","content":"<?xml version=\"1.0\" encoding=\"UTF-8\"?>\n<bpmn:definitions xmlns:bpmn=\"http://www.omg.org/spec/BPMN/20100524/MODEL\" xmlns:bpmndi=\"http://www.omg.org/spec/BPMN/20100524/DI\" xmlns:di=\"http://www.omg.org/spec/DD/20100524/DI\" xmlns:dc=\"http://www.omg.org/spec/DD/20100524/DC\" xmlns:xsi=\"http://www.w3.org/2001/XMLSchema-instance\" xmlns:griffin=\"http://wat\" id=\"Definitions_1\" targetNamespace=\"http://bpmn.io/schema/bpmn\">\n  <bpmn:process id=\"Process_1\" isExecutable=\"false\">\n    <bpmn:startEvent id=\"StartEvent_1\">\n      <bpmn:outgoing>SequenceFlow_0vy2x8y</bpmn:outgoing>\n    </bpmn:startEvent>\n    <bpmn:task id=\"Task_0wyhfye\" name=\"Create Offer\">\n      <bpmn:incoming>SequenceFlow_0vy2x8y</bpmn:incoming>\n      <bpmn:outgoing>SequenceFlow_1uw5t49</bpmn:outgoing>\n      <bpmn:property id=\"Property_1jw42cf\" name=\"__targetRef_placeholder\" />\n      <bpmn:dataInputAssociation id=\"DataInputAssociation_1xdhdnu\">\n        <bpmn:sourceRef>DataObjectReference_1ibxkmu</bpmn:sourceRef>\n        <bpmn:targetRef>Property_1jw42cf</bpmn:targetRef>\n      </bpmn:dataInputAssociation>\n      <bpmn:dataInputAssociation id=\"DataInputAssociation_0er14y8\">\n        <bpmn:sourceRef>DataObjectReference_0ely2ft</bpmn:sourceRef>\n        <bpmn:targetRef>Property_1jw42cf</bpmn:targetRef>\n      </bpmn:dataInputAssociation>\n      <bpmn:dataOutputAssociation id=\"DataOutputAssociation_04x88gm\">\n        <bpmn:targetRef>DataObjectReference_1sfyxrc</bpmn:targetRef>\n      </bpmn:dataOutputAssociation>\n      <bpmn:dataOutputAssociation id=\"DataOutputAssociation_099lcjw\">\n        <bpmn:targetRef>DataObjectReference_1u12glz</bpmn:targetRef>\n      </bpmn:dataOutputAssociation>\n    </bpmn:task>\n    <bpmn:sequenceFlow id=\"SequenceFlow_0vy2x8y\" sourceRef=\"StartEvent_1\" targetRef=\"Task_0wyhfye\" />\n    <bpmn:endEvent id=\"EndEvent_0cah2hq\">\n      <bpmn:incoming>SequenceFlow_1uw5t49</bpmn:incoming>\n    </bpmn:endEvent>\n    <bpmn:sequenceFlow id=\"SequenceFlow_1uw5t49\" sourceRef=\"Task_0wyhfye\" targetRef=\"EndEvent_0cah2hq\" />\n    <bpmn:dataObjectReference id=\"DataObjectReference_1ibxkmu\" name=\"Parcel[new]\" dataObjectRef=\"DataObject_1a1qa3o\" griffin:state=\"new\" griffin:dataclass=\"Parcel\" />\n    <bpmn:dataObject id=\"DataObject_1a1qa3o\" />\n    <bpmn:dataObjectReference id=\"DataObjectReference_0ely2ft\" name=\"Parcel[declined]\" dataObjectRef=\"DataObject_0xutyno\" griffin:state=\"declined\" griffin:dataclass=\"Parcel\" />\n    <bpmn:dataObject id=\"DataObject_0xutyno\" />\n    <bpmn:dataObjectReference id=\"DataObjectReference_1sfyxrc\" name=\"Parcel[offered]\" dataObjectRef=\"DataObject_054vmxo\" griffin:state=\"offered\" griffin:dataclass=\"Parcel\" />\n    <bpmn:dataObject id=\"DataObject_054vmxo\" />\n    <bpmn:dataObjectReference id=\"DataObjectReference_1u12glz\" name=\"Offer[offered]\" dataObjectRef=\"DataObject_1moh3xr\" griffin:state=\"offered\" griffin:dataclass=\"Offer\" />\n    <bpmn:dataObject id=\"DataObject_1moh3xr\" />\n  </bpmn:process>\n  <bpmndi:BPMNDiagram id=\"BPMNDiagram_1\">\n    <bpmndi:BPMNPlane id=\"BPMNPlane_1\" bpmnElement=\"Process_1\">\n      <bpmndi:BPMNShape id=\"_BPMNShape_StartEvent_2\" bpmnElement=\"StartEvent_1\">\n        <dc:Bounds x=\"183\" y=\"173\" width=\"36\" height=\"36\" />\n        <bpmndi:BPMNLabel>\n          <dc:Bounds x=\"156\" y=\"209\" width=\"90\" height=\"20\" />\n        </bpmndi:BPMNLabel>\n      </bpmndi:BPMNShape>\n      <bpmndi:BPMNShape id=\"Task_0wyhfye_di\" bpmnElement=\"Task_0wyhfye\">\n        <dc:Bounds x=\"319\" y=\"151\" width=\"100\" height=\"80\" />\n      </bpmndi:BPMNShape>\n      <bpmndi:BPMNEdge id=\"SequenceFlow_0vy2x8y_di\" bpmnElement=\"SequenceFlow_0vy2x8y\">\n        <di:waypoint x=\"219\" y=\"191\" />\n        <di:waypoint x=\"251\" y=\"191\" />\n        <di:waypoint x=\"251\" y=\"191\" />\n        <di:waypoint x=\"319\" y=\"191\" />\n        <bpmndi:BPMNLabel>\n          <dc:Bounds x=\"201\" y=\"110\" width=\"90\" height=\"20\" />\n        </bpmndi:BPMNLabel>\n      </bpmndi:BPMNEdge>\n      <bpmndi:BPMNShape id=\"EndEvent_0cah2hq_di\" bpmnElement=\"EndEvent_0cah2hq\">\n        <dc:Bounds x=\"535\" y=\"173\" width=\"36\" height=\"36\" />\n        <bpmndi:BPMNLabel>\n          <dc:Bounds x=\"508\" y=\"209\" width=\"90\" height=\"20\" />\n        </bpmndi:BPMNLabel>\n      </bpmndi:BPMNShape>\n      <bpmndi:BPMNEdge id=\"SequenceFlow_1uw5t49_di\" bpmnElement=\"SequenceFlow_1uw5t49\">\n        <di:waypoint x=\"419\" y=\"191\" />\n        <di:waypoint x=\"535\" y=\"191\" />\n        <bpmndi:BPMNLabel>\n          <dc:Bounds x=\"431.5\" y=\"181\" width=\"90\" height=\"20\" />\n        </bpmndi:BPMNLabel>\n      </bpmndi:BPMNEdge>\n      <bpmndi:BPMNShape id=\"DataObjectReference_1ibxkmu_di\" bpmnElement=\"DataObjectReference_1ibxkmu\">\n        <dc:Bounds x=\"233\" y=\"63\" width=\"36\" height=\"50\" />\n        <bpmndi:BPMNLabel>\n          <dc:Bounds x=\"222\" y=\"117\" width=\"58\" height=\"12\" />\n        </bpmndi:BPMNLabel>\n      </bpmndi:BPMNShape>\n      <bpmndi:BPMNEdge id=\"DataInputAssociation_1xdhdnu_di\" bpmnElement=\"DataInputAssociation_1xdhdnu\">\n        <di:waypoint x=\"269\" y=\"102\" />\n        <di:waypoint x=\"330\" y=\"151\" />\n      </bpmndi:BPMNEdge>\n      <bpmndi:BPMNShape id=\"DataObjectReference_0ely2ft_di\" bpmnElement=\"DataObjectReference_0ely2ft\">\n        <dc:Bounds x=\"233\" y=\"261\" width=\"36\" height=\"50\" />\n        <bpmndi:BPMNLabel>\n          <dc:Bounds x=\"212\" y=\"315\" width=\"79\" height=\"12\" />\n        </bpmndi:BPMNLabel>\n      </bpmndi:BPMNShape>\n      <bpmndi:BPMNEdge id=\"DataInputAssociation_0er14y8_di\" bpmnElement=\"DataInputAssociation_0er14y8\">\n        <di:waypoint x=\"269\" y=\"274\" />\n        <di:waypoint x=\"331\" y=\"231\" />\n      </bpmndi:BPMNEdge>\n      <bpmndi:BPMNShape id=\"DataObjectReference_1sfyxrc_di\" bpmnElement=\"DataObjectReference_1sfyxrc\">\n        <dc:Bounds x=\"473\" y=\"63\" width=\"36\" height=\"50\" />\n        <bpmndi:BPMNLabel>\n          <dc:Bounds x=\"455\" y=\"117\" width=\"72\" height=\"12\" />\n        </bpmndi:BPMNLabel>\n      </bpmndi:BPMNShape>\n      <bpmndi:BPMNEdge id=\"DataOutputAssociation_04x88gm_di\" bpmnElement=\"DataOutputAssociation_04x88gm\">\n        <di:waypoint x=\"410\" y=\"152\" />\n        <di:waypoint x=\"473\" y=\"94\" />\n      </bpmndi:BPMNEdge>\n      <bpmndi:BPMNShape id=\"DataObjectReference_1u12glz_di\" bpmnElement=\"DataObjectReference_1u12glz\">\n        <dc:Bounds x=\"473\" y=\"261\" width=\"36\" height=\"50\" />\n        <bpmndi:BPMNLabel>\n          <dc:Bounds x=\"459\" y=\"315\" width=\"65\" height=\"12\" />\n        </bpmndi:BPMNLabel>\n      </bpmndi:BPMNShape>\n      <bpmndi:BPMNEdge id=\"DataOutputAssociation_099lcjw_di\" bpmnElement=\"DataOutputAssociation_099lcjw\">\n        <di:waypoint x=\"415\" y=\"225\" />\n        <di:waypoint x=\"473\" y=\"270\" />\n      </bpmndi:BPMNEdge>\n    </bpmndi:BPMNPlane>\n  </bpmndi:BPMNDiagram>\n</bpmn:definitions>\n","policy":"sequential","automaticActivation":false,"revision":15,"__v":1},{"bound":{"hasBound":false,"limit":100},"preconditions":["Offer[offered]"],"_id":"5cfd52d81991f20025b29aba","name":"Send Offer","content":"<?xml version=\"1.0\" encoding=\"UTF-8\"?>\n<bpmn:definitions xmlns:bpmn=\"http://www.omg.org/spec/BPMN/20100524/MODEL\" xmlns:bpmndi=\"http://www.omg.org/spec/BPMN/20100524/DI\" xmlns:di=\"http://www.omg.org/spec/DD/20100524/DI\" xmlns:dc=\"http://www.omg.org/spec/DD/20100524/DC\" xmlns:xsi=\"http://www.w3.org/2001/XMLSchema-instance\" xmlns:griffin=\"http://wat\" id=\"Definitions_1\" targetNamespace=\"http://bpmn.io/schema/bpmn\">\n  <bpmn:process id=\"Process_1\" isExecutable=\"false\">\n    <bpmn:startEvent id=\"StartEvent_1\">\n      <bpmn:outgoing>SequenceFlow_0vy2x8y</bpmn:outgoing>\n    </bpmn:startEvent>\n    <bpmn:task id=\"Task_0wyhfye\" name=\"Send Offer\">\n      <bpmn:incoming>SequenceFlow_0vy2x8y</bpmn:incoming>\n      <bpmn:outgoing>SequenceFlow_1uw5t49</bpmn:outgoing>\n      <bpmn:property id=\"Property_090ehs5\" name=\"__targetRef_placeholder\" />\n      <bpmn:dataInputAssociation id=\"DataInputAssociation_0kh5ihr\">\n        <bpmn:sourceRef>DataObjectReference_0q7m6h7</bpmn:sourceRef>\n        <bpmn:targetRef>Property_090ehs5</bpmn:targetRef>\n      </bpmn:dataInputAssociation>\n      <bpmn:dataOutputAssociation id=\"DataOutputAssociation_19cuewt\">\n        <bpmn:targetRef>DataObjectReference_1kdrmf2</bpmn:targetRef>\n      </bpmn:dataOutputAssociation>\n      <bpmn:dataOutputAssociation id=\"DataOutputAssociation_0ts338n\">\n        <bpmn:targetRef>DataObjectReference_1wis2c6</bpmn:targetRef>\n      </bpmn:dataOutputAssociation>\n      <bpmn:dataOutputAssociation id=\"DataOutputAssociation_11d1m0n\">\n        <bpmn:targetRef>DataObjectReference_0ukocaj</bpmn:targetRef>\n      </bpmn:dataOutputAssociation>\n    </bpmn:task>\n    <bpmn:sequenceFlow id=\"SequenceFlow_0vy2x8y\" sourceRef=\"StartEvent_1\" targetRef=\"Task_0wyhfye\" />\n    <bpmn:endEvent id=\"EndEvent_0cah2hq\">\n      <bpmn:incoming>SequenceFlow_1uw5t49</bpmn:incoming>\n    </bpmn:endEvent>\n    <bpmn:sequenceFlow id=\"SequenceFlow_1uw5t49\" sourceRef=\"Task_0wyhfye\" targetRef=\"EndEvent_0cah2hq\" />\n    <bpmn:dataObjectReference id=\"DataObjectReference_0q7m6h7\" name=\"Offer[offered]\" dataObjectRef=\"DataObject_0afi04f\" griffin:state=\"offered\" griffin:dataclass=\"Offer\" />\n    <bpmn:dataObject id=\"DataObject_0afi04f\" />\n    <bpmn:dataObjectReference id=\"DataObjectReference_1kdrmf2\" name=\"Offer[accepted]\" dataObjectRef=\"DataObject_1y2xh4q\" griffin:state=\"accepted\" griffin:dataclass=\"Offer\" />\n    <bpmn:dataObject id=\"DataObject_1y2xh4q\" />\n    <bpmn:dataObjectReference id=\"DataObjectReference_1wis2c6\" name=\"Offer[declined]\" dataObjectRef=\"DataObject_0aqy4fr\" griffin:state=\"declined\" griffin:dataclass=\"Offer\" />\n    <bpmn:dataObject id=\"DataObject_0aqy4fr\" />\n    <bpmn:dataObjectReference id=\"DataObjectReference_0ukocaj\" name=\"Offer[timeout]\" dataObjectRef=\"DataObject_0ao12jg\" griffin:state=\"timeout\" griffin:dataclass=\"Offer\" />\n    <bpmn:dataObject id=\"DataObject_0ao12jg\" />\n  </bpmn:process>\n  <bpmndi:BPMNDiagram id=\"BPMNDiagram_1\">\n    <bpmndi:BPMNPlane id=\"BPMNPlane_1\" bpmnElement=\"Process_1\">\n      <bpmndi:BPMNShape id=\"_BPMNShape_StartEvent_2\" bpmnElement=\"StartEvent_1\">\n        <dc:Bounds x=\"183\" y=\"173\" width=\"36\" height=\"36\" />\n        <bpmndi:BPMNLabel>\n          <dc:Bounds x=\"156\" y=\"209\" width=\"90\" height=\"20\" />\n        </bpmndi:BPMNLabel>\n      </bpmndi:BPMNShape>\n      <bpmndi:BPMNShape id=\"Task_0wyhfye_di\" bpmnElement=\"Task_0wyhfye\">\n        <dc:Bounds x=\"319\" y=\"151\" width=\"100\" height=\"80\" />\n      </bpmndi:BPMNShape>\n      <bpmndi:BPMNEdge id=\"SequenceFlow_0vy2x8y_di\" bpmnElement=\"SequenceFlow_0vy2x8y\">\n        <di:waypoint x=\"219\" y=\"191\" />\n        <di:waypoint x=\"251\" y=\"191\" />\n        <di:waypoint x=\"251\" y=\"191\" />\n        <di:waypoint x=\"319\" y=\"191\" />\n        <bpmndi:BPMNLabel>\n          <dc:Bounds x=\"201\" y=\"110\" width=\"90\" height=\"20\" />\n        </bpmndi:BPMNLabel>\n      </bpmndi:BPMNEdge>\n      <bpmndi:BPMNShape id=\"EndEvent_0cah2hq_di\" bpmnElement=\"EndEvent_0cah2hq\">\n        <dc:Bounds x=\"535\" y=\"173\" width=\"36\" height=\"36\" />\n        <bpmndi:BPMNLabel>\n          <dc:Bounds x=\"508\" y=\"209\" width=\"90\" height=\"20\" />\n        </bpmndi:BPMNLabel>\n      </bpmndi:BPMNShape>\n      <bpmndi:BPMNEdge id=\"SequenceFlow_1uw5t49_di\" bpmnElement=\"SequenceFlow_1uw5t49\">\n        <di:waypoint x=\"419\" y=\"191\" />\n        <di:waypoint x=\"535\" y=\"191\" />\n        <bpmndi:BPMNLabel>\n          <dc:Bounds x=\"431.5\" y=\"181\" width=\"90\" height=\"20\" />\n        </bpmndi:BPMNLabel>\n      </bpmndi:BPMNEdge>\n      <bpmndi:BPMNShape id=\"DataObjectReference_0q7m6h7_di\" bpmnElement=\"DataObjectReference_0q7m6h7\">\n        <dc:Bounds x=\"233\" y=\"66\" width=\"36\" height=\"50\" />\n        <bpmndi:BPMNLabel>\n          <dc:Bounds x=\"219\" y=\"120\" width=\"65\" height=\"12\" />\n        </bpmndi:BPMNLabel>\n      </bpmndi:BPMNShape>\n      <bpmndi:BPMNEdge id=\"DataInputAssociation_0kh5ihr_di\" bpmnElement=\"DataInputAssociation_0kh5ihr\">\n        <di:waypoint x=\"269\" y=\"105\" />\n        <di:waypoint x=\"328\" y=\"152\" />\n      </bpmndi:BPMNEdge>\n      <bpmndi:BPMNShape id=\"DataObjectReference_1kdrmf2_di\" bpmnElement=\"DataObjectReference_1kdrmf2\">\n        <dc:Bounds x=\"466\" y=\"66\" width=\"36\" height=\"50\" />\n        <bpmndi:BPMNLabel>\n          <dc:Bounds x=\"446\" y=\"120\" width=\"76\" height=\"12\" />\n        </bpmndi:BPMNLabel>\n      </bpmndi:BPMNShape>\n      <bpmndi:BPMNEdge id=\"DataOutputAssociation_19cuewt_di\" bpmnElement=\"DataOutputAssociation_19cuewt\">\n        <di:waypoint x=\"412\" y=\"154\" />\n        <di:waypoint x=\"466\" y=\"107\" />\n      </bpmndi:BPMNEdge>\n      <bpmndi:BPMNShape id=\"DataObjectReference_1wis2c6_di\" bpmnElement=\"DataObjectReference_1wis2c6\">\n        <dc:Bounds x=\"466\" y=\"268\" width=\"36\" height=\"50\" />\n        <bpmndi:BPMNLabel>\n          <dc:Bounds x=\"448\" y=\"322\" width=\"72\" height=\"12\" />\n        </bpmndi:BPMNLabel>\n      </bpmndi:BPMNShape>\n      <bpmndi:BPMNEdge id=\"DataOutputAssociation_0ts338n_di\" bpmnElement=\"DataOutputAssociation_0ts338n\">\n        <di:waypoint x=\"413\" y=\"227\" />\n        <di:waypoint x=\"466\" y=\"269\" />\n      </bpmndi:BPMNEdge>\n      <bpmndi:BPMNShape id=\"DataObjectReference_0ukocaj_di\" bpmnElement=\"DataObjectReference_0ukocaj\">\n        <dc:Bounds x=\"466\" y=\"411.07433217189316\" width=\"36\" height=\"50\" />\n        <bpmndi:BPMNLabel>\n          <dc:Bounds x=\"451\" y=\"465\" width=\"67\" height=\"12\" />\n        </bpmndi:BPMNLabel>\n      </bpmndi:BPMNShape>\n      <bpmndi:BPMNEdge id=\"DataOutputAssociation_11d1m0n_di\" bpmnElement=\"DataOutputAssociation_11d1m0n\">\n        <di:waypoint x=\"387\" y=\"231\" />\n        <di:waypoint x=\"466\" y=\"412\" />\n      </bpmndi:BPMNEdge>\n    </bpmndi:BPMNPlane>\n  </bpmndi:BPMNDiagram>\n</bpmn:definitions>\n","policy":"sequential","automaticActivation":false,"revision":13,"__v":1},{"bound":{"hasBound":false,"limit":100},"preconditions":["Offer[accepted]"],"_id":"5cfd55b91991f20025b29ac3","name":"Send Parcel","content":"<?xml version=\"1.0\" encoding=\"UTF-8\"?>\n<bpmn:definitions xmlns:bpmn=\"http://www.omg.org/spec/BPMN/20100524/MODEL\" xmlns:bpmndi=\"http://www.omg.org/spec/BPMN/20100524/DI\" xmlns:di=\"http://www.omg.org/spec/DD/20100524/DI\" xmlns:dc=\"http://www.omg.org/spec/DD/20100524/DC\" xmlns:xsi=\"http://www.w3.org/2001/XMLSchema-instance\" xmlns:griffin=\"http://wat\" id=\"Definitions_1\" targetNamespace=\"http://bpmn.io/schema/bpmn\">\n  <bpmn:process id=\"Process_1\" isExecutable=\"false\">\n    <bpmn:startEvent id=\"StartEvent_1\">\n      <bpmn:outgoing>SequenceFlow_0vy2x8y</bpmn:outgoing>\n    </bpmn:startEvent>\n    <bpmn:task id=\"Task_0wyhfye\" name=\"Send Parcel\">\n      <bpmn:incoming>SequenceFlow_0vy2x8y</bpmn:incoming>\n      <bpmn:outgoing>SequenceFlow_1uw5t49</bpmn:outgoing>\n      <bpmn:property id=\"Property_00jzxq2\" name=\"__targetRef_placeholder\" />\n      <bpmn:dataInputAssociation id=\"DataInputAssociation_0827gjs\">\n        <bpmn:sourceRef>DataObjectReference_1n9j8bx</bpmn:sourceRef>\n        <bpmn:targetRef>Property_00jzxq2</bpmn:targetRef>\n      </bpmn:dataInputAssociation>\n      <bpmn:dataInputAssociation id=\"DataInputAssociation_0xh1asd\">\n        <bpmn:sourceRef>DataObjectReference_0banvr6</bpmn:sourceRef>\n        <bpmn:targetRef>Property_00jzxq2</bpmn:targetRef>\n      </bpmn:dataInputAssociation>\n      <bpmn:dataOutputAssociation id=\"DataOutputAssociation_0pxj1ef\">\n        <bpmn:targetRef>DataObjectReference_06vvu95</bpmn:targetRef>\n      </bpmn:dataOutputAssociation>\n    </bpmn:task>\n    <bpmn:sequenceFlow id=\"SequenceFlow_0vy2x8y\" sourceRef=\"StartEvent_1\" targetRef=\"Task_0wyhfye\" />\n    <bpmn:endEvent id=\"EndEvent_0cah2hq\">\n      <bpmn:incoming>SequenceFlow_1uw5t49</bpmn:incoming>\n    </bpmn:endEvent>\n    <bpmn:sequenceFlow id=\"SequenceFlow_1uw5t49\" sourceRef=\"Task_0wyhfye\" targetRef=\"EndEvent_0cah2hq\" />\n    <bpmn:dataObjectReference id=\"DataObjectReference_1n9j8bx\" name=\"Parcel[offered]\" dataObjectRef=\"DataObject_19pqcqo\" griffin:state=\"offered\" griffin:dataclass=\"Parcel\" />\n    <bpmn:dataObject id=\"DataObject_19pqcqo\" />\n    <bpmn:dataObjectReference id=\"DataObjectReference_0banvr6\" name=\"Offer[accepted]\" dataObjectRef=\"DataObject_1pxbbbt\" griffin:state=\"accepted\" griffin:dataclass=\"Offer\" />\n    <bpmn:dataObject id=\"DataObject_1pxbbbt\" />\n    <bpmn:dataObjectReference id=\"DataObjectReference_06vvu95\" name=\"Parcel[sent]\" dataObjectRef=\"DataObject_07vpooh\" griffin:state=\"sent\" griffin:dataclass=\"Parcel\" />\n    <bpmn:dataObject id=\"DataObject_07vpooh\" />\n  </bpmn:process>\n  <bpmndi:BPMNDiagram id=\"BPMNDiagram_1\">\n    <bpmndi:BPMNPlane id=\"BPMNPlane_1\" bpmnElement=\"Process_1\">\n      <bpmndi:BPMNShape id=\"_BPMNShape_StartEvent_2\" bpmnElement=\"StartEvent_1\">\n        <dc:Bounds x=\"183\" y=\"173\" width=\"36\" height=\"36\" />\n        <bpmndi:BPMNLabel>\n          <dc:Bounds x=\"156\" y=\"209\" width=\"90\" height=\"20\" />\n        </bpmndi:BPMNLabel>\n      </bpmndi:BPMNShape>\n      <bpmndi:BPMNShape id=\"Task_0wyhfye_di\" bpmnElement=\"Task_0wyhfye\">\n        <dc:Bounds x=\"319\" y=\"151\" width=\"100\" height=\"80\" />\n      </bpmndi:BPMNShape>\n      <bpmndi:BPMNEdge id=\"SequenceFlow_0vy2x8y_di\" bpmnElement=\"SequenceFlow_0vy2x8y\">\n        <di:waypoint x=\"219\" y=\"191\" />\n        <di:waypoint x=\"251\" y=\"191\" />\n        <di:waypoint x=\"251\" y=\"191\" />\n        <di:waypoint x=\"319\" y=\"191\" />\n        <bpmndi:BPMNLabel>\n          <dc:Bounds x=\"201\" y=\"110\" width=\"90\" height=\"20\" />\n        </bpmndi:BPMNLabel>\n      </bpmndi:BPMNEdge>\n      <bpmndi:BPMNShape id=\"EndEvent_0cah2hq_di\" bpmnElement=\"EndEvent_0cah2hq\">\n        <dc:Bounds x=\"535\" y=\"173\" width=\"36\" height=\"36\" />\n        <bpmndi:BPMNLabel>\n          <dc:Bounds x=\"508\" y=\"209\" width=\"90\" height=\"20\" />\n        </bpmndi:BPMNLabel>\n      </bpmndi:BPMNShape>\n      <bpmndi:BPMNEdge id=\"SequenceFlow_1uw5t49_di\" bpmnElement=\"SequenceFlow_1uw5t49\">\n        <di:waypoint x=\"419\" y=\"191\" />\n        <di:waypoint x=\"535\" y=\"191\" />\n        <bpmndi:BPMNLabel>\n          <dc:Bounds x=\"431.5\" y=\"181\" width=\"90\" height=\"20\" />\n        </bpmndi:BPMNLabel>\n      </bpmndi:BPMNEdge>\n      <bpmndi:BPMNShape id=\"DataObjectReference_1n9j8bx_di\" bpmnElement=\"DataObjectReference_1n9j8bx\">\n        <dc:Bounds x=\"254\" y=\"53\" width=\"36\" height=\"50\" />\n        <bpmndi:BPMNLabel>\n          <dc:Bounds x=\"236\" y=\"107\" width=\"72\" height=\"12\" />\n        </bpmndi:BPMNLabel>\n      </bpmndi:BPMNShape>\n      <bpmndi:BPMNEdge id=\"DataInputAssociation_0827gjs_di\" bpmnElement=\"DataInputAssociation_0827gjs\">\n        <di:waypoint x=\"290\" y=\"100\" />\n        <di:waypoint x=\"332\" y=\"151\" />\n      </bpmndi:BPMNEdge>\n      <bpmndi:BPMNShape id=\"DataObjectReference_0banvr6_di\" bpmnElement=\"DataObjectReference_0banvr6\">\n        <dc:Bounds x=\"254\" y=\"273\" width=\"36\" height=\"50\" />\n        <bpmndi:BPMNLabel>\n          <dc:Bounds x=\"234\" y=\"327\" width=\"76\" height=\"12\" />\n        </bpmndi:BPMNLabel>\n      </bpmndi:BPMNShape>\n      <bpmndi:BPMNEdge id=\"DataInputAssociation_0xh1asd_di\" bpmnElement=\"DataInputAssociation_0xh1asd\">\n        <di:waypoint x=\"290\" y=\"279\" />\n        <di:waypoint x=\"334\" y=\"231\" />\n      </bpmndi:BPMNEdge>\n      <bpmndi:BPMNShape id=\"DataObjectReference_06vvu95_di\" bpmnElement=\"DataObjectReference_06vvu95\">\n        <dc:Bounds x=\"464\" y=\"53\" width=\"36\" height=\"50\" />\n        <bpmndi:BPMNLabel>\n          <dc:Bounds x=\"453\" y=\"107\" width=\"59\" height=\"12\" />\n        </bpmndi:BPMNLabel>\n      </bpmndi:BPMNShape>\n      <bpmndi:BPMNEdge id=\"DataOutputAssociation_0pxj1ef_di\" bpmnElement=\"DataOutputAssociation_0pxj1ef\">\n        <di:waypoint x=\"409\" y=\"151\" />\n        <di:waypoint x=\"464\" y=\"96\" />\n      </bpmndi:BPMNEdge>\n    </bpmndi:BPMNPlane>\n  </bpmndi:BPMNDiagram>\n</bpmn:definitions>\n","policy":"sequential","automaticActivation":false,"revision":5,"__v":1},{"bound":{"hasBound":false,"limit":100},"preconditions":["Offer[declined]"],"_id":"5cfd57091991f20025b29ac4","name":"Removing Parcel","content":"<?xml version=\"1.0\" encoding=\"UTF-8\"?>\n<bpmn:definitions xmlns:bpmn=\"http://www.omg.org/spec/BPMN/20100524/MODEL\" xmlns:bpmndi=\"http://www.omg.org/spec/BPMN/20100524/DI\" xmlns:di=\"http://www.omg.org/spec/DD/20100524/DI\" xmlns:dc=\"http://www.omg.org/spec/DD/20100524/DC\" xmlns:xsi=\"http://www.w3.org/2001/XMLSchema-instance\" xmlns:griffin=\"http://wat\" id=\"Definitions_1\" targetNamespace=\"http://bpmn.io/schema/bpmn\">\n  <bpmn:process id=\"Process_1\" isExecutable=\"false\">\n    <bpmn:startEvent id=\"StartEvent_1\">\n      <bpmn:outgoing>SequenceFlow_0vy2x8y</bpmn:outgoing>\n    </bpmn:startEvent>\n    <bpmn:task id=\"Task_0wyhfye\" name=\"Remove Parcel\">\n      <bpmn:incoming>SequenceFlow_0vy2x8y</bpmn:incoming>\n      <bpmn:outgoing>SequenceFlow_1uw5t49</bpmn:outgoing>\n      <bpmn:property id=\"Property_1cf4h1m\" name=\"__targetRef_placeholder\" />\n      <bpmn:dataInputAssociation id=\"DataInputAssociation_0ycx3cw\">\n        <bpmn:sourceRef>DataObjectReference_1gxumga</bpmn:sourceRef>\n        <bpmn:targetRef>Property_1cf4h1m</bpmn:targetRef>\n      </bpmn:dataInputAssociation>\n      <bpmn:dataInputAssociation id=\"DataInputAssociation_1fth5bn\">\n        <bpmn:sourceRef>DataObjectReference_0143f7x</bpmn:sourceRef>\n        <bpmn:targetRef>Property_1cf4h1m</bpmn:targetRef>\n      </bpmn:dataInputAssociation>\n      <bpmn:dataInputAssociation id=\"DataInputAssociation_00q7e9a\">\n        <bpmn:sourceRef>DataObjectReference_0tp7meq</bpmn:sourceRef>\n        <bpmn:targetRef>Property_1cf4h1m</bpmn:targetRef>\n      </bpmn:dataInputAssociation>\n      <bpmn:dataOutputAssociation id=\"DataOutputAssociation_0owbdpx\">\n        <bpmn:targetRef>DataObjectReference_1vk35f5</bpmn:targetRef>\n      </bpmn:dataOutputAssociation>\n    </bpmn:task>\n    <bpmn:sequenceFlow id=\"SequenceFlow_0vy2x8y\" sourceRef=\"StartEvent_1\" targetRef=\"Task_0wyhfye\" />\n    <bpmn:endEvent id=\"EndEvent_0cah2hq\">\n      <bpmn:incoming>SequenceFlow_1uw5t49</bpmn:incoming>\n    </bpmn:endEvent>\n    <bpmn:sequenceFlow id=\"SequenceFlow_1uw5t49\" sourceRef=\"Task_0wyhfye\" targetRef=\"EndEvent_0cah2hq\" />\n    <bpmn:dataObjectReference id=\"DataObjectReference_1gxumga\" name=\"Parcel[offered]\" dataObjectRef=\"DataObject_0kgj9u1\" griffin:state=\"offered\" griffin:dataclass=\"Parcel\" />\n    <bpmn:dataObject id=\"DataObject_0kgj9u1\" />\n    <bpmn:dataObjectReference id=\"DataObjectReference_0143f7x\" name=\"Offer[declined]\" dataObjectRef=\"DataObject_07faian\" griffin:state=\"declined\" griffin:dataclass=\"Offer\" />\n    <bpmn:dataObject id=\"DataObject_07faian\" />\n    <bpmn:dataObjectReference id=\"DataObjectReference_1vk35f5\" name=\"Parcel[declined]\" dataObjectRef=\"DataObject_0zshcvl\" griffin:state=\"declined\" griffin:dataclass=\"Parcel\" />\n    <bpmn:dataObject id=\"DataObject_0zshcvl\" />\n    <bpmn:dataObjectReference id=\"DataObjectReference_0tp7meq\" name=\"Offer[timeout]\" dataObjectRef=\"DataObject_0rn8phj\" griffin:state=\"timeout\" griffin:dataclass=\"Offer\" />\n    <bpmn:dataObject id=\"DataObject_0rn8phj\" />\n  </bpmn:process>\n  <bpmndi:BPMNDiagram id=\"BPMNDiagram_1\">\n    <bpmndi:BPMNPlane id=\"BPMNPlane_1\" bpmnElement=\"Process_1\">\n      <bpmndi:BPMNShape id=\"_BPMNShape_StartEvent_2\" bpmnElement=\"StartEvent_1\">\n        <dc:Bounds x=\"183\" y=\"173\" width=\"36\" height=\"36\" />\n        <bpmndi:BPMNLabel>\n          <dc:Bounds x=\"156\" y=\"209\" width=\"90\" height=\"20\" />\n        </bpmndi:BPMNLabel>\n      </bpmndi:BPMNShape>\n      <bpmndi:BPMNShape id=\"Task_0wyhfye_di\" bpmnElement=\"Task_0wyhfye\">\n        <dc:Bounds x=\"319\" y=\"151\" width=\"100\" height=\"80\" />\n      </bpmndi:BPMNShape>\n      <bpmndi:BPMNEdge id=\"SequenceFlow_0vy2x8y_di\" bpmnElement=\"SequenceFlow_0vy2x8y\">\n        <di:waypoint x=\"219\" y=\"191\" />\n        <di:waypoint x=\"251\" y=\"191\" />\n        <di:waypoint x=\"251\" y=\"191\" />\n        <di:waypoint x=\"319\" y=\"191\" />\n        <bpmndi:BPMNLabel>\n          <dc:Bounds x=\"201\" y=\"110\" width=\"90\" height=\"20\" />\n        </bpmndi:BPMNLabel>\n      </bpmndi:BPMNEdge>\n      <bpmndi:BPMNShape id=\"EndEvent_0cah2hq_di\" bpmnElement=\"EndEvent_0cah2hq\">\n        <dc:Bounds x=\"535\" y=\"173\" width=\"36\" height=\"36\" />\n        <bpmndi:BPMNLabel>\n          <dc:Bounds x=\"508\" y=\"209\" width=\"90\" height=\"20\" />\n        </bpmndi:BPMNLabel>\n      </bpmndi:BPMNShape>\n      <bpmndi:BPMNEdge id=\"SequenceFlow_1uw5t49_di\" bpmnElement=\"SequenceFlow_1uw5t49\">\n        <di:waypoint x=\"419\" y=\"191\" />\n        <di:waypoint x=\"535\" y=\"191\" />\n        <bpmndi:BPMNLabel>\n          <dc:Bounds x=\"431.5\" y=\"181\" width=\"90\" height=\"20\" />\n        </bpmndi:BPMNLabel>\n      </bpmndi:BPMNEdge>\n      <bpmndi:BPMNShape id=\"DataObjectReference_1gxumga_di\" bpmnElement=\"DataObjectReference_1gxumga\">\n        <dc:Bounds x=\"244\" y=\"66\" width=\"36\" height=\"50\" />\n        <bpmndi:BPMNLabel>\n          <dc:Bounds x=\"226\" y=\"120\" width=\"72\" height=\"12\" />\n        </bpmndi:BPMNLabel>\n      </bpmndi:BPMNShape>\n      <bpmndi:BPMNEdge id=\"DataInputAssociation_0ycx3cw_di\" bpmnElement=\"DataInputAssociation_0ycx3cw\">\n        <di:waypoint x=\"280\" y=\"108\" />\n        <di:waypoint x=\"327\" y=\"153\" />\n      </bpmndi:BPMNEdge>\n      <bpmndi:BPMNShape id=\"DataObjectReference_0143f7x_di\" bpmnElement=\"DataObjectReference_0143f7x\">\n        <dc:Bounds x=\"244\" y=\"274\" width=\"36\" height=\"50\" />\n        <bpmndi:BPMNLabel>\n          <dc:Bounds x=\"226\" y=\"328\" width=\"72\" height=\"12\" />\n        </bpmndi:BPMNLabel>\n      </bpmndi:BPMNShape>\n      <bpmndi:BPMNEdge id=\"DataInputAssociation_1fth5bn_di\" bpmnElement=\"DataInputAssociation_1fth5bn\">\n        <di:waypoint x=\"280\" y=\"283\" />\n        <di:waypoint x=\"340\" y=\"231\" />\n      </bpmndi:BPMNEdge>\n      <bpmndi:BPMNShape id=\"DataObjectReference_1vk35f5_di\" bpmnElement=\"DataObjectReference_1vk35f5\">\n        <dc:Bounds x=\"467\" y=\"66\" width=\"36\" height=\"50\" />\n        <bpmndi:BPMNLabel>\n          <dc:Bounds x=\"446\" y=\"120\" width=\"79\" height=\"12\" />\n        </bpmndi:BPMNLabel>\n      </bpmndi:BPMNShape>\n      <bpmndi:BPMNEdge id=\"DataOutputAssociation_0owbdpx_di\" bpmnElement=\"DataOutputAssociation_0owbdpx\">\n        <di:waypoint x=\"411\" y=\"153\" />\n        <di:waypoint x=\"467\" y=\"101\" />\n      </bpmndi:BPMNEdge>\n      <bpmndi:BPMNShape id=\"DataObjectReference_0tp7meq_di\" bpmnElement=\"DataObjectReference_0tp7meq\">\n        <dc:Bounds x=\"315\" y=\"328\" width=\"36\" height=\"50\" />\n        <bpmndi:BPMNLabel>\n          <dc:Bounds x=\"300\" y=\"382\" width=\"67\" height=\"12\" />\n        </bpmndi:BPMNLabel>\n      </bpmndi:BPMNShape>\n      <bpmndi:BPMNEdge id=\"DataInputAssociation_00q7e9a_di\" bpmnElement=\"DataInputAssociation_00q7e9a\">\n        <di:waypoint x=\"336\" y=\"328\" />\n        <di:waypoint x=\"347\" y=\"231\" />\n      </bpmndi:BPMNEdge>\n    </bpmndi:BPMNPlane>\n  </bpmndi:BPMNDiagram>\n</bpmn:definitions>\n","policy":"sequential","automaticActivation":false,"revision":7,"__v":1}],"_id":"5cfc10241991f20025b29ab7","name":"Parcel Delivery Translation","description":"","revision":4,"startconditions":[],"domainmodel":{"_id":"5cfc10241991f20025b29ab8","dataclasses":[{"attributes":[],"_id":"5cfd53431991f20025b29abc","name":"Parcel","is_event":false,"olc":{"intermediateThrowEvent":[{"id":"State_11u8x6w","name":"new","outgoing":["SequenceFlow_1d9kpvm"]},{"id":"State_0x8fy3i","name":"offered","incoming":["SequenceFlow_1d9kpvm","SequenceFlow_1lmhd5q"],"outgoing":["SequenceFlow_0q83ykj","SequenceFlow_0eavdqq"]},{"id":"State_1q72j71","name":"sent","incoming":["SequenceFlow_0q83ykj"]},{"id":"State_14l5ft1","name":"declined","incoming":["SequenceFlow_0eavdqq"],"outgoing":["SequenceFlow_1lmhd5q"]}],"sequenceFlow":[{"id":"SequenceFlow_1d9kpvm","sourceRef":"State_11u8x6w","targetRef":"State_0x8fy3i"},{"id":"SequenceFlow_0q83ykj","sourceRef":"State_0x8fy3i","targetRef":"State_1q72j71"},{"id":"SequenceFlow_0eavdqq","sourceRef":"State_0x8fy3i","targetRef":"State_14l5ft1"},{"id":"SequenceFlow_1lmhd5q","sourceRef":"State_14l5ft1","targetRef":"State_0x8fy3i"}],"state":[{"id":"State_11u8x6w","name":"new","outgoing":["SequenceFlow_1d9kpvm"]},{"id":"State_0x8fy3i","name":"offered","incoming":["SequenceFlow_1d9kpvm","SequenceFlow_1lmhd5q"],"outgoing":["SequenceFlow_0q83ykj","SequenceFlow_0eavdqq"]},{"id":"State_1q72j71","name":"sent","incoming":["SequenceFlow_0q83ykj"]},{"id":"State_14l5ft1","name":"declined","incoming":["SequenceFlow_0eavdqq"],"outgoing":["SequenceFlow_1lmhd5q"]}],"content":"<?xml version=\"1.0\" encoding=\"UTF-8\"?>\n<bpmn:definitions xmlns:bpmn=\"http://www.omg.org/spec/BPMN/20100524/MODEL\" xmlns:bpmndi=\"http://www.omg.org/spec/BPMN/20100524/DI\" xmlns:di=\"http://www.omg.org/spec/DD/20100524/DI\" xmlns:dc=\"http://www.omg.org/spec/DD/20100524/DC\" xmlns:xsi=\"http://www.w3.org/2001/XMLSchema-instance\" id=\"Definitions_1\" targetNamespace=\"http://bpmn.io/schema/bpmn\">\n  <bpmn:process id=\"Process_1\" isExecutable=\"false\">\n    <bpmn:intermediateThrowEvent id=\"IntermediateThrowEvent_11u8x6w\" name=\"new\">\n      <bpmn:outgoing>SequenceFlow_1d9kpvm</bpmn:outgoing>\n    </bpmn:intermediateThrowEvent>\n    <bpmn:intermediateThrowEvent id=\"IntermediateThrowEvent_0x8fy3i\" name=\"offered\">\n      <bpmn:incoming>SequenceFlow_1d9kpvm</bpmn:incoming>\n      <bpmn:incoming>SequenceFlow_1lmhd5q</bpmn:incoming>\n      <bpmn:outgoing>SequenceFlow_0q83ykj</bpmn:outgoing>\n      <bpmn:outgoing>SequenceFlow_0eavdqq</bpmn:outgoing>\n    </bpmn:intermediateThrowEvent>\n    <bpmn:sequenceFlow id=\"SequenceFlow_1d9kpvm\" sourceRef=\"IntermediateThrowEvent_11u8x6w\" targetRef=\"IntermediateThrowEvent_0x8fy3i\" />\n    <bpmn:intermediateThrowEvent id=\"IntermediateThrowEvent_1q72j71\" name=\"sent\">\n      <bpmn:incoming>SequenceFlow_0q83ykj</bpmn:incoming>\n    </bpmn:intermediateThrowEvent>\n    <bpmn:sequenceFlow id=\"SequenceFlow_0q83ykj\" sourceRef=\"IntermediateThrowEvent_0x8fy3i\" targetRef=\"IntermediateThrowEvent_1q72j71\" />\n    <bpmn:intermediateThrowEvent id=\"IntermediateThrowEvent_14l5ft1\" name=\"declined\">\n      <bpmn:incoming>SequenceFlow_0eavdqq</bpmn:incoming>\n      <bpmn:outgoing>SequenceFlow_1lmhd5q</bpmn:outgoing>\n    </bpmn:intermediateThrowEvent>\n    <bpmn:sequenceFlow id=\"SequenceFlow_0eavdqq\" sourceRef=\"IntermediateThrowEvent_0x8fy3i\" targetRef=\"IntermediateThrowEvent_14l5ft1\" />\n    <bpmn:sequenceFlow id=\"SequenceFlow_1lmhd5q\" sourceRef=\"IntermediateThrowEvent_14l5ft1\" targetRef=\"IntermediateThrowEvent_0x8fy3i\" />\n  </bpmn:process>\n  <bpmndi:BPMNDiagram id=\"BPMNDiagram_1\">\n    <bpmndi:BPMNPlane id=\"BPMNPlane_1\" bpmnElement=\"Process_1\">\n      <bpmndi:BPMNEdge id=\"DataOutputAssociation_12dthu6_di\">\n        <di:waypoint x=\"152\" y=\"175\" />\n        <di:waypoint x=\"183\" y=\"99\" />\n      </bpmndi:BPMNEdge>\n      <bpmndi:BPMNEdge id=\"DataOutputAssociation_1dwvspi_di\">\n        <di:waypoint x=\"145\" y=\"173\" />\n        <di:waypoint x=\"145\" y=\"120\" />\n      </bpmndi:BPMNEdge>\n      <bpmndi:BPMNEdge id=\"DataOutputAssociation_0n341tu_di\">\n        <di:waypoint x=\"145\" y=\"173\" />\n        <di:waypoint x=\"145\" y=\"120\" />\n      </bpmndi:BPMNEdge>\n      <bpmndi:BPMNEdge id=\"DataOutputAssociation_04283jp_di\">\n        <di:waypoint x=\"145\" y=\"173\" />\n        <di:waypoint x=\"145\" y=\"120\" />\n      </bpmndi:BPMNEdge>\n      <bpmndi:BPMNShape id=\"IntermediateThrowEvent_11u8x6w_di\" bpmnElement=\"IntermediateThrowEvent_11u8x6w\">\n        <dc:Bounds x=\"201\" y=\"120\" width=\"36\" height=\"36\" />\n        <bpmndi:BPMNLabel>\n          <dc:Bounds x=\"209\" y=\"156\" width=\"22\" height=\"12\" />\n        </bpmndi:BPMNLabel>\n      </bpmndi:BPMNShape>\n      <bpmndi:BPMNShape id=\"IntermediateThrowEvent_0x8fy3i_di\" bpmnElement=\"IntermediateThrowEvent_0x8fy3i\">\n        <dc:Bounds x=\"348\" y=\"120\" width=\"36\" height=\"36\" />\n        <bpmndi:BPMNLabel>\n          <dc:Bounds x=\"349\" y=\"156\" width=\"35\" height=\"12\" />\n        </bpmndi:BPMNLabel>\n      </bpmndi:BPMNShape>\n      <bpmndi:BPMNEdge id=\"SequenceFlow_1d9kpvm_di\" bpmnElement=\"SequenceFlow_1d9kpvm\">\n        <di:waypoint x=\"237\" y=\"138\" />\n        <di:waypoint x=\"348\" y=\"138\" />\n        <bpmndi:BPMNLabel>\n          <dc:Bounds x=\"247.5\" y=\"113\" width=\"90\" height=\"20\" />\n        </bpmndi:BPMNLabel>\n      </bpmndi:BPMNEdge>\n      <bpmndi:BPMNShape id=\"IntermediateThrowEvent_1q72j71_di\" bpmnElement=\"IntermediateThrowEvent_1q72j71\">\n        <dc:Bounds x=\"473\" y=\"120\" width=\"36\" height=\"36\" />\n        <bpmndi:BPMNLabel>\n          <dc:Bounds x=\"481\" y=\"160\" width=\"22\" height=\"12\" />\n        </bpmndi:BPMNLabel>\n      </bpmndi:BPMNShape>\n      <bpmndi:BPMNEdge id=\"SequenceFlow_0q83ykj_di\" bpmnElement=\"SequenceFlow_0q83ykj\">\n        <di:waypoint x=\"384\" y=\"138\" />\n        <di:waypoint x=\"473\" y=\"138\" />\n        <bpmndi:BPMNLabel>\n          <dc:Bounds x=\"428.5\" y=\"117\" width=\"0\" height=\"12\" />\n        </bpmndi:BPMNLabel>\n      </bpmndi:BPMNEdge>\n      <bpmndi:BPMNShape id=\"IntermediateThrowEvent_14l5ft1_di\" bpmnElement=\"IntermediateThrowEvent_14l5ft1\">\n        <dc:Bounds x=\"348\" y=\"9\" width=\"36\" height=\"36\" />\n        <bpmndi:BPMNLabel>\n          <dc:Bounds x=\"345\" y=\"49\" width=\"42\" height=\"12\" />\n        </bpmndi:BPMNLabel>\n      </bpmndi:BPMNShape>\n      <bpmndi:BPMNEdge id=\"SequenceFlow_0eavdqq_di\" bpmnElement=\"SequenceFlow_0eavdqq\">\n        <di:waypoint x=\"355\" y=\"124\" />\n        <di:waypoint x=\"317\" y=\"73\" />\n        <di:waypoint x=\"353\" y=\"39\" />\n        <bpmndi:BPMNLabel>\n          <dc:Bounds x=\"336\" y=\"77.5\" width=\"0\" height=\"12\" />\n        </bpmndi:BPMNLabel>\n      </bpmndi:BPMNEdge>\n      <bpmndi:BPMNEdge id=\"SequenceFlow_1lmhd5q_di\" bpmnElement=\"SequenceFlow_1lmhd5q\">\n        <di:waypoint x=\"379\" y=\"39\" />\n        <di:waypoint x=\"418\" y=\"75\" />\n        <di:waypoint x=\"377\" y=\"124\" />\n        <bpmndi:BPMNLabel>\n          <dc:Bounds x=\"398.5\" y=\"36\" width=\"0\" height=\"12\" />\n        </bpmndi:BPMNLabel>\n      </bpmndi:BPMNEdge>\n    </bpmndi:BPMNPlane>\n  </bpmndi:BPMNDiagram>\n</bpmn:definitions>\n"}},{"attributes":[],"_id":"5cfd534b1991f20025b29abd","name":"Offer","is_event":false,"olc":{"intermediateThrowEvent":[{"id":"State_11u8x6w","name":"offered","outgoing":["SequenceFlow_1d9kpvm","SequenceFlow_19e5y1c","SequenceFlow_0ndt5di"]},{"id":"State_0x8fy3i","name":"accepted","incoming":["SequenceFlow_1d9kpvm"]},{"id":"State_04ifl5q","name":"declined","incoming":["SequenceFlow_19e5y1c"]},{"id":"State_1cznnw7","name":"timeout","incoming":["SequenceFlow_0ndt5di"]}],"sequenceFlow":[{"id":"SequenceFlow_1d9kpvm","sourceRef":"State_11u8x6w","targetRef":"State_0x8fy3i"},{"id":"SequenceFlow_19e5y1c","sourceRef":"State_11u8x6w","targetRef":"State_04ifl5q"},{"id":"SequenceFlow_0ndt5di","sourceRef":"State_11u8x6w","targetRef":"State_1cznnw7"}],"state":[{"id":"State_11u8x6w","name":"offered","outgoing":["SequenceFlow_1d9kpvm","SequenceFlow_19e5y1c","SequenceFlow_0ndt5di"]},{"id":"State_0x8fy3i","name":"accepted","incoming":["SequenceFlow_1d9kpvm"]},{"id":"State_04ifl5q","name":"declined","incoming":["SequenceFlow_19e5y1c"]},{"id":"State_1cznnw7","name":"timeout","incoming":["SequenceFlow_0ndt5di"]}],"content":"<?xml version=\"1.0\" encoding=\"UTF-8\"?>\n<bpmn:definitions xmlns:bpmn=\"http://www.omg.org/spec/BPMN/20100524/MODEL\" xmlns:bpmndi=\"http://www.omg.org/spec/BPMN/20100524/DI\" xmlns:di=\"http://www.omg.org/spec/DD/20100524/DI\" xmlns:dc=\"http://www.omg.org/spec/DD/20100524/DC\" xmlns:xsi=\"http://www.w3.org/2001/XMLSchema-instance\" id=\"Definitions_1\" targetNamespace=\"http://bpmn.io/schema/bpmn\">\n  <bpmn:process id=\"Process_1\" isExecutable=\"false\">\n    <bpmn:intermediateThrowEvent id=\"IntermediateThrowEvent_11u8x6w\" name=\"offered\">\n      <bpmn:outgoing>SequenceFlow_1d9kpvm</bpmn:outgoing>\n      <bpmn:outgoing>SequenceFlow_19e5y1c</bpmn:outgoing>\n      <bpmn:outgoing>SequenceFlow_0ndt5di</bpmn:outgoing>\n    </bpmn:intermediateThrowEvent>\n    <bpmn:intermediateThrowEvent id=\"IntermediateThrowEvent_0x8fy3i\" name=\"accepted\">\n      <bpmn:incoming>SequenceFlow_1d9kpvm</bpmn:incoming>\n    </bpmn:intermediateThrowEvent>\n    <bpmn:sequenceFlow id=\"SequenceFlow_1d9kpvm\" sourceRef=\"IntermediateThrowEvent_11u8x6w\" targetRef=\"IntermediateThrowEvent_0x8fy3i\" />\n    <bpmn:intermediateThrowEvent id=\"IntermediateThrowEvent_04ifl5q\" name=\"declined\">\n      <bpmn:incoming>SequenceFlow_19e5y1c</bpmn:incoming>\n    </bpmn:intermediateThrowEvent>\n    <bpmn:sequenceFlow id=\"SequenceFlow_19e5y1c\" sourceRef=\"IntermediateThrowEvent_11u8x6w\" targetRef=\"IntermediateThrowEvent_04ifl5q\" />\n    <bpmn:intermediateThrowEvent id=\"IntermediateThrowEvent_1cznnw7\" name=\"timeout\">\n      <bpmn:incoming>SequenceFlow_0ndt5di</bpmn:incoming>\n    </bpmn:intermediateThrowEvent>\n    <bpmn:sequenceFlow id=\"SequenceFlow_0ndt5di\" sourceRef=\"IntermediateThrowEvent_11u8x6w\" targetRef=\"IntermediateThrowEvent_1cznnw7\" />\n  </bpmn:process>\n  <bpmndi:BPMNDiagram id=\"BPMNDiagram_1\">\n    <bpmndi:BPMNPlane id=\"BPMNPlane_1\" bpmnElement=\"Process_1\">\n      <bpmndi:BPMNEdge id=\"DataOutputAssociation_12dthu6_di\">\n        <di:waypoint x=\"152\" y=\"175\" />\n        <di:waypoint x=\"183\" y=\"99\" />\n      </bpmndi:BPMNEdge>\n      <bpmndi:BPMNEdge id=\"DataOutputAssociation_1dwvspi_di\">\n        <di:waypoint x=\"145\" y=\"173\" />\n        <di:waypoint x=\"145\" y=\"120\" />\n      </bpmndi:BPMNEdge>\n      <bpmndi:BPMNEdge id=\"DataOutputAssociation_0n341tu_di\">\n        <di:waypoint x=\"145\" y=\"173\" />\n        <di:waypoint x=\"145\" y=\"120\" />\n      </bpmndi:BPMNEdge>\n      <bpmndi:BPMNEdge id=\"DataOutputAssociation_04283jp_di\">\n        <di:waypoint x=\"145\" y=\"173\" />\n        <di:waypoint x=\"145\" y=\"120\" />\n      </bpmndi:BPMNEdge>\n      <bpmndi:BPMNShape id=\"IntermediateThrowEvent_11u8x6w_di\" bpmnElement=\"IntermediateThrowEvent_11u8x6w\">\n        <dc:Bounds x=\"201\" y=\"120\" width=\"36\" height=\"36\" />\n        <bpmndi:BPMNLabel>\n          <dc:Bounds x=\"202\" y=\"156\" width=\"35\" height=\"12\" />\n        </bpmndi:BPMNLabel>\n      </bpmndi:BPMNShape>\n      <bpmndi:BPMNShape id=\"IntermediateThrowEvent_0x8fy3i_di\" bpmnElement=\"IntermediateThrowEvent_0x8fy3i\">\n        <dc:Bounds x=\"406\" y=\"120\" width=\"36\" height=\"36\" />\n        <bpmndi:BPMNLabel>\n          <dc:Bounds x=\"402\" y=\"156\" width=\"45\" height=\"12\" />\n        </bpmndi:BPMNLabel>\n      </bpmndi:BPMNShape>\n      <bpmndi:BPMNEdge id=\"SequenceFlow_1d9kpvm_di\" bpmnElement=\"SequenceFlow_1d9kpvm\">\n        <di:waypoint x=\"237\" y=\"138\" />\n        <di:waypoint x=\"342\" y=\"138\" />\n        <di:waypoint x=\"342\" y=\"138\" />\n        <di:waypoint x=\"406\" y=\"138\" />\n        <bpmndi:BPMNLabel>\n          <dc:Bounds x=\"440\" y=\"186\" width=\"90\" height=\"20\" />\n        </bpmndi:BPMNLabel>\n      </bpmndi:BPMNEdge>\n      <bpmndi:BPMNShape id=\"IntermediateThrowEvent_04ifl5q_di\" bpmnElement=\"IntermediateThrowEvent_04ifl5q\">\n        <dc:Bounds x=\"406\" y=\"31\" width=\"36\" height=\"36\" />\n        <bpmndi:BPMNLabel>\n          <dc:Bounds x=\"403\" y=\"71\" width=\"42\" height=\"12\" />\n        </bpmndi:BPMNLabel>\n      </bpmndi:BPMNShape>\n      <bpmndi:BPMNEdge id=\"SequenceFlow_19e5y1c_di\" bpmnElement=\"SequenceFlow_19e5y1c\">\n        <di:waypoint x=\"219\" y=\"120\" />\n        <di:waypoint x=\"219\" y=\"49\" />\n        <di:waypoint x=\"406\" y=\"49\" />\n        <bpmndi:BPMNLabel>\n          <dc:Bounds x=\"234\" y=\"78.5\" width=\"0\" height=\"12\" />\n        </bpmndi:BPMNLabel>\n      </bpmndi:BPMNEdge>\n      <bpmndi:BPMNShape id=\"IntermediateThrowEvent_1cznnw7_di\" bpmnElement=\"IntermediateThrowEvent_1cznnw7\">\n        <dc:Bounds x=\"406\" y=\"216.57839721254356\" width=\"36\" height=\"36\" />\n        <bpmndi:BPMNLabel>\n          <dc:Bounds x=\"405\" y=\"257\" width=\"38\" height=\"12\" />\n        </bpmndi:BPMNLabel>\n      </bpmndi:BPMNShape>\n      <bpmndi:BPMNEdge id=\"SequenceFlow_0ndt5di_di\" bpmnElement=\"SequenceFlow_0ndt5di\">\n        <di:waypoint x=\"219\" y=\"156\" />\n        <di:waypoint x=\"219\" y=\"235\" />\n        <di:waypoint x=\"406\" y=\"235\" />\n        <bpmndi:BPMNLabel>\n          <dc:Bounds x=\"234\" y=\"189.5\" width=\"0\" height=\"12\" />\n        </bpmndi:BPMNLabel>\n      </bpmndi:BPMNEdge>\n    </bpmndi:BPMNPlane>\n  </bpmndi:BPMNDiagram>\n</bpmn:definitions>\n"}}],"revision":6,"name":"Parcel Delivery Translation","__v":5},"__v":3}